{"nodes": [{"id": "home_ethos_coding_pyrst_test_all_sh", "label": "test_all.sh", "file_type": "code", "source_file": "test_all.sh", "source_location": "L1", "metadata": {"language": "bash", "kind": "file"}}, {"id": "home_ethos_coding_pyrst_test_all_sh__entry", "label": "test_all.sh script", "file_type": "code", "source_file": "test_all.sh", "source_location": "L1", "metadata": {"language": "bash", "kind": "bash_entrypoint"}}, {"id": "pyrst_test_all_assert_output", "label": "assert_output()", "file_type": "code", "source_file": "test_all.sh", "source_location": "L37", "metadata": {"language": "bash", "kind": "bash_function"}}], "edges": [{"source": "home_ethos_coding_pyrst_test_all_sh", "target": "home_ethos_coding_pyrst_test_all_sh__entry", "relation": "contains", "confidence": "EXTRACTED", "source_file": "test_all.sh", "source_location": "L1", "weight": 1.0}, {"source": "home_ethos_coding_pyrst_test_all_sh", "target": "pyrst_test_all_assert_output", "relation": "defines", "confidence": "EXTRACTED", "source_file": "test_all.sh", "source_location": "L37", "weight": 1.0}, {"source": "home_ethos_coding_pyrst_test_all_sh__entry", "target": "pyrst_test_all_assert_output", "relation": "calls", "confidence": "EXTRACTED", "source_file": "test_all.sh", "source_location": "L52", "weight": 1.0, "context": "call"}]}